stun/__init__.py
stun/client.py
stun/node.py
stun/server.py
stun/protocol/__init__.py
stun/protocol/attributes.py
stun/protocol/header.py
stun/protocol/package.py
stun/protocol/values.py
stun/tlv/__init__.py
stun/tlv/entry.py
stun/tlv/length.py
stun/tlv/parser.py
stun/tlv/tag.py
stun/tlv/value.py
stun/turn/__init__.py
stun/turn/values.py
stun-0.2.3.dist-info/METADATA
stun-0.2.3.dist-info/WHEEL
stun-0.2.3.dist-info/top_level.txt
stun-0.2.3.dist-info/RECORD
