Metadata-Version: 2.1
Name: stun
Version: 0.2.3
Summary: Session Traversal Utilities for NAT
Home-page: https://github.com/moky/wormhole/
Author: Albert Moky
Author-email: albert.moky@gmail.com
License: MIT
Platform: UNKNOWN
Classifier: Programming Language :: Python :: 3
Classifier: License :: OSI Approved :: MIT License
Classifier: Operating System :: OS Independent
